micropython_si7021/__init__.py
micropython_si7021/si7021.py
micropython_si7021-0.1.2.dist-info/LICENSE
micropython_si7021-0.1.2.dist-info/METADATA
micropython_si7021-0.1.2.dist-info/WHEEL
micropython_si7021-0.1.2.dist-info/top_level.txt
micropython_si7021-0.1.2.dist-info/RECORD
