Metadata-Version: 2.1
Name: micropython-si7021
Version: 0.1.2
Summary: MicroPython Library for the the Temperature and Humidity SI7021 Sensor
Author-email: "Jose D. Montoya" <si7021@mailmeto.mozmail.com>
License: MIT
Project-URL: Homepage, https://github.com/jposada202020/MicroPython_SI7021
Keywords: micropython,micropython_si7021,si7021,sensor,temperature,humidity
Classifier: Intended Audience :: Developers
Classifier: Topic :: Software Development :: Libraries
Classifier: Topic :: Software Development :: Embedded Systems
Classifier: Topic :: System :: Hardware
Classifier: License :: OSI Approved :: MIT License
Classifier: Programming Language :: Python :: Implementation :: MicroPython
License-File: LICENSE
